pastdays/__init__.py
pastdays/engine.py
pastdays/features.py
pastdays/loader.py
pastdays/report.py
pastdays/similarity.py
pastdays-0.0.1.dist-info/METADATA
pastdays-0.0.1.dist-info/WHEEL
pastdays-0.0.1.dist-info/top_level.txt
pastdays-0.0.1.dist-info/RECORD
