Metadata-Version: 2.4
Name: pastdays
Version: 0.0.1
Summary: Find past market days similar to today using historical data
Author: Anurag Mishra
License-Expression: MIT
Project-URL: Homepage, https://github.com/anuragnitw6/pastdays
Project-URL: Repository, https://github.com/anuragnitw6/pastdays
Project-URL: Issues, https://github.com/anuragnitw6/pastdays/issues
Keywords: trading,backtesting,market-analysis,time-series,finance
Classifier: Development Status :: 3 - Alpha
Classifier: Intended Audience :: Developers
Classifier: Intended Audience :: Financial and Insurance Industry
Classifier: Programming Language :: Python :: 3
Classifier: Programming Language :: Python :: 3.8
Classifier: Programming Language :: Python :: 3.9
Classifier: Programming Language :: Python :: 3.10
Classifier: Programming Language :: Python :: 3.11
Classifier: Topic :: Scientific/Engineering :: Information Analysis
Requires-Python: >=3.8
Requires-Dist: pandas>=1.5
Requires-Dist: numpy>=1.21
